gutils/__init__.py
gutils/components.py
gutils/fixed_size_list.py
gutils/two_way_dict.py
gutils/logger/__init__.py
gutils/tests/test_fixed_list.py
gutils-0.1.9.dist-info/LICENSE
gutils-0.1.9.dist-info/METADATA
gutils-0.1.9.dist-info/WHEEL
gutils-0.1.9.dist-info/top_level.txt
gutils-0.1.9.dist-info/RECORD
